src/__init__.py
src/main.py
src/server.py
src/shared.py
src/executor/__init__.py
src/executor/k6.py
src/executor/parser.py
src/storage/__init__.py
src/storage/file.py
src/tools/__init__.py
src/tools/baseline.py
src/tools/batch.py
src/tools/environment.py
src/tools/quick.py
src/tools/scenario.py
src/tools/system.py
src/tools/test.py
src/utils/__init__.py
src/utils/cleanup.py
src/utils/curl_parser.py
src/utils/format.py
k6_mcp-1.0.0.dist-info/METADATA
k6_mcp-1.0.0.dist-info/WHEEL
k6_mcp-1.0.0.dist-info/entry_points.txt
k6_mcp-1.0.0.dist-info/RECORD
