Metadata-Version: 2.4
Name: k6-mcp
Version: 1.0.0
Summary: Enhanced K6 MCP server for load testing with natural language in Cursor
Project-URL: Homepage, https://gitee.com/chang-xinping/k6-mcp
Project-URL: Repository, https://gitee.com/chang-xinping/k6-mcp
Author-email: Douzi <1492994674@qq.com>
License: MIT
Keywords: ai,cursor,k6,load-testing,mcp,performance
Classifier: Development Status :: 4 - Beta
Classifier: Intended Audience :: Developers
Classifier: License :: OSI Approved :: MIT License
Classifier: Programming Language :: Python :: 3
Classifier: Programming Language :: Python :: 3.10
Classifier: Programming Language :: Python :: 3.11
Classifier: Programming Language :: Python :: 3.12
Classifier: Topic :: Software Development :: Testing
Requires-Python: >=3.10
Requires-Dist: aiohttp>=3.9.0
Requires-Dist: mcp>=1.0.0
Requires-Dist: pydantic>=2.0.0
